buanzobasics/__init__.py
buanzobasics/buanzobasics.py
buanzobasics-0.1.0.dist-info/DESCRIPTION.rst
buanzobasics-0.1.0.dist-info/METADATA
buanzobasics-0.1.0.dist-info/RECORD
buanzobasics-0.1.0.dist-info/WHEEL
buanzobasics-0.1.0.dist-info/metadata.json
buanzobasics-0.1.0.dist-info/top_level.txt
