Metadata-Version: 2.0
Name: buanzobasics
Version: 0.1.0
Summary: A couple of useful functions like printerr, pprinterr, envOrDefault, etc
Home-page: https://github.com/buanzo/basics
Author: Arturo "Buanzo" Busleiman
Author-email: buanzo@buanzo.com.ar
License: APL
Keywords: python3,utility
Platform: UNKNOWN
Classifier: Intended Audience :: Developers
Classifier: Natural Language :: English
Classifier: Operating System :: POSIX :: Linux
Classifier: Operating System :: POSIX :: Other
Classifier: Operating System :: POSIX
Classifier: Programming Language :: Python
Classifier: Programming Language :: Python :: 3 :: Only
Classifier: Programming Language :: Python :: 3.6
Classifier: Programming Language :: Python :: 3.7
Classifier: Programming Language :: Python :: 3.8
Classifier: Programming Language :: Python :: Implementation :: PyPy
Requires-Python: >=3.6
